.DS_Store
.git/COMMIT_EDITMSG
.git/HEAD
.git/config
.git/description
.git/hooks/applypatch-msg.sample
.git/hooks/commit-msg.sample
.git/hooks/fsmonitor-watchman.sample
.git/hooks/post-update.sample
.git/hooks/pre-applypatch.sample
.git/hooks/pre-commit.sample
.git/hooks/pre-merge-commit.sample
.git/hooks/pre-push.sample
.git/hooks/pre-rebase.sample
.git/hooks/pre-receive.sample
.git/hooks/prepare-commit-msg.sample
.git/hooks/push-to-checkout.sample
.git/hooks/update.sample
.git/index
.git/info/exclude
.git/logs/HEAD
.git/logs/refs/heads/main
.git/logs/refs/remotes/origin/main
.git/objects/00/115e0250d0cf8b625617fe6faa56b8d1aeff62
.git/objects/00/2e111d6ab1b9c48589cda48da2cfd4d40880a0
.git/objects/00/8112568285b01aa5cb6f357dcc94f278e0767d
.git/objects/00/e6238af4285012d1848b199667f1a1c9506a4e
.git/objects/01/4c02cbd4de8dfe4bbf7bc3a010adac402930d2
.git/objects/01/c4d910a5c644642e60e174049f890f09257e95
.git/objects/01/ea0e58f9113659e2f8510b83ff111a8b71f819
.git/objects/01/fe7f289d319ac8ed8defa11d36834770f02dcd
.git/objects/02/5e99e840494579d42fa759434c6e7afbea3035
.git/objects/02/62933bf9456eec5dd1d82e6148e60c0e3f861b
.git/objects/03/0d661c0f80aa22e083401da1458187c721d121
.git/objects/03/741c23e0efe9f505962714f24a24359450fe31
.git/objects/03/a53855f14a48344bfc4b8d0dcabb5a020707c2
.git/objects/04/92e7c93d06e8b8d286d77f6f9687fde2d6fb96
.git/objects/06/32c02dc981e41ed4b618b944e1421e99983d14
.git/objects/06/4daf822d41241ba02c1329e4ab55ed2851f6c8
.git/objects/06/75baf99997a277638c3feb97d73be3e5a5e2be
.git/objects/06/7d09d476b5ad4550110b476e4553f394c884ab
.git/objects/06/e0241702380a109bfdb45cc3823f38f15f8de7
.git/objects/07/7eaacb33adeaf66fcca7dd4538deb784fe38f3
.git/objects/07/9910c83da61839e6c5217582db8b9c236b4d8a
.git/objects/07/f26e511e19c5185b9cee400dc4cbc401544876
.git/objects/07/fe0d43c6213468e2ef88f65f9e805f5b24366f
.git/objects/08/a473cc20d923651f0134e1ac3954d4406af66a
.git/objects/09/18277fb4f2a6716388310eb3ad296017c09254
pyemr-0.3.6.dist-info/entry_points.txt
pyemr-0.3.6.dist-info/WHEEL
pyemr-0.3.6.dist-info/METADATA
pyemr-0.3.6.dist-info/RECORD
