Metadata-Version: 2.1
Name: pyemr
Version: 0.3.6
Summary: A lightweight package for running poetry projects on emr.
Author: Richard Brooker
Author-email: richjbrooker@gmail.com
Requires-Python: >=3.7.1,<3.9
Classifier: Programming Language :: Python :: 3
Classifier: Programming Language :: Python :: 3.8
Requires-Dist: Jinja2 (>=3.0.3,<4.0.0)
Requires-Dist: Pygments (>=2.10.0,<3.0.0)
Requires-Dist: autocorrect (>=2.6.1,<3.0.0)
Requires-Dist: autopep8 (>=1.6.0,<2.0.0)
Requires-Dist: awswrangler (>=2.0.0,<3.0.0)
Requires-Dist: black (>=21.12b0,<22.0)
Requires-Dist: boto3 (>=1.20.23,<2.0.0)
Requires-Dist: brunette (>=0.2.2,<0.3.0)
Requires-Dist: cron-descriptor (>=1.2.24,<2.0.0)
Requires-Dist: datefinder (>=0.7.1,<0.8.0)
Requires-Dist: docker (>=5.0.3,<6.0.0)
Requires-Dist: findspark (>=1.4.2,<2.0.0)
Requires-Dist: fire (>=0.4.0,<0.5.0)
Requires-Dist: ipykernel (>=6.6.0,<7.0.0)
Requires-Dist: loguru (>=0.5.3,<0.6.0)
Requires-Dist: numpy (==1.18.0)
Requires-Dist: pandas (>=1.1.0,<2.0.0)
Requires-Dist: pexpect (>=4.8.0,<5.0.0)
Requires-Dist: poetry (>=1.1.12,<2.0.0)
Requires-Dist: pyenchant (>=3.2.2,<4.0.0)
Requires-Dist: pylint (>=2.12.2,<3.0.0)
Requires-Dist: setuptools (>=60.5.0,<61.0.0)
Requires-Dist: sh (>=1.14.2,<2.0.0)
Requires-Dist: termcolor (>=1.1.0,<2.0.0)
Requires-Dist: tomlkit (==0.7.2)
Requires-Dist: tqdm (>=4.62.3,<5.0.0)
Requires-Dist: xdoctest (>=0.15.10,<0.16.0)
